bspwm_auto_rice/autoricer.py
bspwm_auto_rice/bspar.py
bspwm_auto_rice/dependencies.py
bspwm_auto_rice-0.1.2.post3.dist-info/entry_points.txt
bspwm_auto_rice-0.1.2.post3.dist-info/LICENSE
bspwm_auto_rice-0.1.2.post3.dist-info/WHEEL
bspwm_auto_rice-0.1.2.post3.dist-info/METADATA
bspwm_auto_rice-0.1.2.post3.dist-info/RECORD
